magenpy-0.1.5.dist-info/RECORD
magenpy-0.1.5.dist-info/WHEEL
magenpy-0.1.5.dist-info/top_level.txt
magenpy-0.1.5.dist-info/METADATA
magenpy-0.1.5.dist-info/licenses/LICENSE
magenpy-0.1.5.data/scripts/magenpy_ld
magenpy-0.1.5.data/scripts/magenpy_simulate
magenpy/SumstatsTable.py
magenpy/GWADataLoader.py
magenpy/GenotypeMatrix.py
magenpy/SampleTable.py
magenpy/__init__.py
magenpy/AnnotationMatrix.py
magenpy/LDMatrix.py
magenpy/LDLinearOperator.py
magenpy/parsers/misc_parsers.py
magenpy/parsers/__init__.py
magenpy/parsers/annotation_parsers.py
magenpy/parsers/sumstats_parsers.py
magenpy/parsers/plink_parsers.py
magenpy/plot/ld.py
magenpy/plot/gwa.py
magenpy/plot/__init__.py
magenpy/config/paths.ini
magenpy/simulation/MultiCohortPhenotypeSimulator.py
magenpy/simulation/__init__.py
magenpy/simulation/PhenotypeSimulator.py
magenpy/simulation/AnnotatedPhenotypeSimulator.py
magenpy/utils/model_utils.py
magenpy/utils/compute_utils.py
magenpy/utils/__init__.py
magenpy/utils/system_utils.py
magenpy/utils/executors.py
magenpy/utils/data_utils.py
magenpy/data/lrld_hg19_GRCh37.txt
magenpy/data/1000G_eur_chr22.bed
magenpy/data/1000G_eur_chr22.fam
magenpy/data/1000G_eur_chr22.bim
magenpy/data/ukb_height_chr22.fastGWA.gz
magenpy/stats/__init__.py
magenpy/stats/h2/__init__.py
magenpy/stats/h2/ldsc.py
magenpy/stats/ld/__init__.py
magenpy/stats/ld/c_utils.cpython-312-darwin.so
magenpy/stats/ld/utils.py
magenpy/stats/ld/estimator.py
magenpy/stats/gwa/__init__.py
magenpy/stats/gwa/utils.py
magenpy/stats/score/__init__.py
magenpy/stats/score/utils.py
magenpy/stats/transforms/genotype.py
magenpy/stats/transforms/__init__.py
magenpy/stats/transforms/phenotype.py
magenpy/stats/variant/__init__.py
magenpy/stats/variant/utils.py
