Metadata-Version: 2.4
Name: magenpy
Version: 0.1.5
Summary: Modeling and Analysis of Statistical Genetics data in python
Home-page: https://github.com/shz9/magenpy
Author: Shadi Zabad
Author-email: shadi.zabad@mail.mcgill.ca
Classifier: Programming Language :: Python
Classifier: Intended Audience :: Developers
Classifier: Intended Audience :: Science/Research
Classifier: Topic :: Software Development :: Libraries :: Python Modules
Classifier: Topic :: Scientific/Engineering
Classifier: Operating System :: OS Independent
Classifier: Programming Language :: Python :: 3
Classifier: Programming Language :: Python :: 3.8
Classifier: Programming Language :: Python :: 3.9
Classifier: Programming Language :: Python :: 3.10
Classifier: Programming Language :: Python :: 3.11
Classifier: Programming Language :: Python :: 3.12
Requires-Python: >=3.8
License-File: LICENSE
Requires-Dist: dask<=2024.1.0
Requires-Dist: scipy
Requires-Dist: numpy<2
Requires-Dist: joblib
Requires-Dist: pandas
Requires-Dist: pandas-plink
Requires-Dist: psutil
Requires-Dist: tqdm
Requires-Dist: zarr<3
Provides-Extra: opt
Requires-Dist: matplotlib; extra == "opt"
Requires-Dist: seaborn; extra == "opt"
Requires-Dist: statsmodels; extra == "opt"
Requires-Dist: s3fs; extra == "opt"
Provides-Extra: test
Requires-Dist: pytest; extra == "test"
Provides-Extra: docs
Requires-Dist: mkdocs; extra == "docs"
Requires-Dist: mkdocstrings-python; extra == "docs"
Requires-Dist: mkdocs-material; extra == "docs"
Requires-Dist: mkdocs-material-extensions; extra == "docs"
Dynamic: author
Dynamic: author-email
Dynamic: classifier
Dynamic: description
Dynamic: description-content-type
Dynamic: home-page
Dynamic: license-file
Dynamic: provides-extra
Dynamic: requires-dist
Dynamic: requires-python
Dynamic: summary
